amk/rfwd/__init__.py
amk/rfwd/arg_parse.py
amk/rfwd/consts.py
amk/rfwd/logger.py
amk.rfwd-1.0.0.dist-info/LICENSE
amk.rfwd-1.0.0.dist-info/METADATA
amk.rfwd-1.0.0.dist-info/WHEEL
amk.rfwd-1.0.0.dist-info/entry_points.txt
amk.rfwd-1.0.0.dist-info/top_level.txt
amk.rfwd-1.0.0.dist-info/RECORD
