Metadata-Version: 2.1
Name: amk.rfwd
Version: 1.0.0
Summary: Rename Files With Date
Home-page: https://github.com/AndyM129/rename_files_with_date
Author: Andy Meng
Author-email: andy_m129@163.com
License: GNU General Public License v3.0
Platform: UNKNOWN
Requires-Python: >=3.9
License-File: LICENSE
Requires-Dist: colorama
